mesh_to_depth/io_utils.py
mesh_to_depth/ctypes_mesh2depth.py
mesh_to_depth/__init__.py
mesh_to_depth/log.py
mesh_to_depth/libmesh2depth.so
mesh_to_depth-0.1.2.dist-info/top_level.txt
mesh_to_depth-0.1.2.dist-info/WHEEL
mesh_to_depth-0.1.2.dist-info/LICENSE
mesh_to_depth-0.1.2.dist-info/RECORD
mesh_to_depth-0.1.2.dist-info/METADATA
