Metadata-Version: 2.1
Name: mesh-to-depth
Version: 0.1.2
Summary: Generate depth maps, given a mesh and camera parameters
Home-page: https://github.com/daeyun/mesh_to_depth
Author: Daeyun Shin
Author-email: daeyuns@uci.edu
License: UNKNOWN
Platform: UNKNOWN
Requires-Python: >=3.6
Requires-Dist: numpy
Requires-Dist: setuptools
Requires-Dist: networkx
Requires-Dist: trimesh
Requires-Dist: pillow
Provides-Extra: test
Requires-Dist: pytest ; extra == 'test'
